fastfs/__init__.py
fastfs/config.py
fastfs/main.py
fastfs/models/__init__.py
fastfs/models/file_models.py
fastfs/public/__init__.py
fastfs/public/app.css
fastfs/services/__init__.py
fastfs/services/file_service.py
fastfs/utils/__init__.py
fastfs/utils/helpers.py
fastfs/views/__init__.py
fastfs/views/renderers.py
python_fastfs-0.1.1.dist-info/LICENSE
python_fastfs-0.1.1.dist-info/METADATA
python_fastfs-0.1.1.dist-info/WHEEL
python_fastfs-0.1.1.dist-info/entry_points.txt
python_fastfs-0.1.1.dist-info/RECORD
