Metadata-Version: 2.1
Name: python-fastfs
Version: 0.1.1
Summary: 
Author: jc_nana
Author-email: joshuakt.mit@gmail.com
Requires-Python: >=3.10,<4.0
Classifier: Programming Language :: Python :: 3
Classifier: Programming Language :: Python :: 3.10
Classifier: Programming Language :: Python :: 3.11
Classifier: Programming Language :: Python :: 3.12
Requires-Dist: pydantic (>=2.9.1,<3.0.0)
Requires-Dist: pydantic-settings (>=2.5.2,<3.0.0)
Requires-Dist: python-fasthtml (>=0.5.2,<0.6.0)
